group01_lab05_part2/reg_file.v
module reg_file(OUT2ADDRESS, OUT1ADDRESS,INADDRESS,IN,WRITE,CLOCK,RESET,OUT1,OUT2);
    input [2:0] OUT2ADDRESS, OUT1ADDRESS, INADDRESS;
    input [7:0] IN;
    input WRITE, CLOCK, RESET;
    output [7:0] OUT1, OUT2;

    reg [7:0] REGISTER [7:0];

    integer i;

    assign #2 OUT1 = REGISTER[OUT1ADDRESS];
    assign #2 OUT2 = REGISTER[OUT2ADDRESS];

    always @(posedge CLOCK)
    begin
    // Synchronous register operations (Write and Reset)
        if (RESET == 1'b1)
        begin
            #1 for (i = 0; i < 8; i = i + 1)
            begin
                REGISTER[i] <= 8'b00000000;
            end
        end
        else if (WRITE == 1'b1)
        begin
            #1 REGISTER[INADDRESS] <= IN;
        end
    end 
endmodule

group01_lab05_part2/reg_file_tb.v
// Computer Architecture (CO224) - Lab 05
// Design: Register File of Simple Processor
// Author: Kisaru Liyanage
`include "reg_file.v"
module reg_file_tb;
    
    reg [7:0] WRITEDATA;
    reg [2:0] WRITEREG, READREG1, READREG2;
    reg CLK, RESET, WRITEENABLE; 
    wire [7:0] REGOUT1, REGOUT2;
    //OUT2ADDRESS, OUT1ADDRESS,INADDRESS,IN,WRITE,CLOCK,RESET,OUT1,OUT2
    reg_file myregfile(READREG2,READREG1,WRITEREG,WRITEDATA,WRITEENABLE,CLK,RESET,REGOUT1,REGOUT2);
    integer i;

    initial
    begin
        CLK = 1'b1;
        
        // generate files needed to plot the waveform using GTKWave
        $dumpfile("reg_file_wavedata.vcd");
		$dumpvars(0, reg_file_tb);

        for(i=0; i<8;i++)
            $dumpvars(1, reg_file_tb.myregfile.REGISTER[i]);

        // assign values with time to input signals to see output 
        RESET = 1'b0;
        WRITEENABLE = 1'b0;
        
        #4
        RESET = 1'b1;
        READREG1 = 3'd0;
        READREG2 = 3'd4;
        
        #6
        RESET = 1'b0;
        
        #2
        WRITEREG = 3'd2;
        WRITEDATA = 8'd95;
        WRITEENABLE = 1'b1;
        
        #7
        WRITEENABLE = 1'b0;
        
        #1
        READREG1 = 3'd2;
        
        #7
        WRITEREG = 3'd1;
        WRITEDATA = 8'd28;
        WRITEENABLE = 1'b1;
        READREG1 = 3'd1;
        
        #8
        WRITEENABLE = 1'b0;
        
        #8
        WRITEREG = 3'd4;
        WRITEDATA = 8'd6;
        WRITEENABLE = 1'b1;
        
        #8
        WRITEDATA = 8'd15;
        WRITEENABLE = 1'b1;
        
        #10
        WRITEENABLE = 1'b0;
        
        #6
        WRITEREG = -3'd1;
        WRITEDATA = 8'd50;
        WRITEENABLE = 1'b1;
        
        #5
        WRITEENABLE = 1'b0;
        
        #10
        $finish;
    end
    
    // clock signal generation
    always
        #4 CLK = ~CLK;
        

endmodule

group01_lab05_part2/reg_file_wavedata.vcd
$date
	Wed Apr 10 13:05:40 2024
$end
$version
	Icarus Verilog
$end
$timescale
	1s
$end
$scope module reg_file_tb $end
$var wire 8 ! REGOUT2 [7:0] $end
$var wire 8 " REGOUT1 [7:0] $end
$var reg 1 # CLK $end
$var reg 3 $ READREG1 [2:0] $end
$var reg 3 % READREG2 [2:0] $end
$var reg 1 & RESET $end
$var reg 8 ' WRITEDATA [7:0] $end
$var reg 1 ( WRITEENABLE $end
$var reg 3 ) WRITEREG [2:0] $end
$var integer 32 * i [31:0] $end
$scope module myregfile $end
$var wire 1 # CLOCK $end
$var wire 8 + IN [7:0] $end
$var wire 3 , INADDRESS [2:0] $end
$var wire 8 - OUT1 [7:0] $end
$var wire 3 . OUT1ADDRESS [2:0] $end
$var wire 8 / OUT2 [7:0] $end
$var wire 3 0 OUT2ADDRESS [2:0] $end
$var wire 1 & RESET $end
$var wire 1 ( WRITE $end
$var integer 32 1 i [31:0] $end
$upscope $end
$upscope $end
$scope module reg_file_tb $end
$scope module myregfile $end
$var reg 8 2 \REGISTER[0] [7:0] $end
$upscope $end
$upscope $end
$scope module reg_file_tb $end
$scope module myregfile $end
$var reg 8 3 \REGISTER[1] [7:0] $end
$upscope $end
$upscope $end
$scope module reg_file_tb $end
$scope module myregfile $end
$var reg 8 4 \REGISTER[2] [7:0] $end
$upscope $end
$upscope $end
$scope module reg_file_tb $end
$scope module myregfile $end
$var reg 8 5 \REGISTER[3] [7:0] $end
$upscope $end
$upscope $end
$scope module reg_file_tb $end
$scope module myregfile $end
$var reg 8 6 \REGISTER[4] [7:0] $end
$upscope $end
$upscope $end
$scope module reg_file_tb $end
$scope module myregfile $end
$var reg 8 7 \REGISTER[5] [7:0] $end
$upscope $end
$upscope $end
$scope module reg_file_tb $end
$scope module myregfile $end
$var reg 8 8 \REGISTER[6] [7:0] $end
$upscope $end
$upscope $end
$scope module reg_file_tb $end
$scope module myregfile $end
$var reg 8 9 \REGISTER[7] [7:0] $end
$upscope $end
$upscope $end
$enddefinitions $end
$comment Show the parameter values. $end
$dumpall
$end
#0
$dumpvars
bx 9
bx 8
bx 7
bx 6
bx 5
bx 4
bx 3
bx 2
bx 1
bx 0
bx /
bx .
bx -
bx ,
bx +
b1000 *
bx )
0(
bx '
0&
bx %
bx $
1#
bx "
bx !
$end
#4
0#
b100 %
b100 0
b0 $
b0 .
1&
#8
1#
#9
b0 9
b0 8
b0 7
b0 6
b0 5
b0 4
b0 3
b0 2
b1000 1
#10
0&
#11
b0 !
b0 /
b0 "
b0 -
#12
1(
b1011111 '
b1011111 +
b10 )
b10 ,
0#
#16
1#
#17
b1011111 4
#19
0(
#20
b10 $
b10 .
0#
#22
b1011111 "
b1011111 -
#24
1#
#27
b1 $
b1 .
1(
b11100 '
b11100 +
b1 )
b1 ,
#28
0#
#29
b0 "
b0 -
#32
1#
#33
b11100 3
#35
b11100 "
b11100 -
0(
#36
0#
#40
1#
#43
1(
b110 '
b110 +
b100 )
b100 ,
#44
0#
#48
1#
#49
b110 6
#51
b110 !
b110 /
b1111 '
b1111 +
#52
0#
#56
1#
#57
b1111 6
#59
b1111 !
b1111 /
#60
0#
#61
0(
#64
1#
#67
1(
b110010 '
b110010 +
b111 )
b111 ,
#68
0#
#72
1#
0(
